modules/or7.v
module OR7 (
    input  a, b, c, d, e, f, g,
    output y
);
    assign y = a | b | c | d | e | f | g;
endmodule

modules/or6.v
module OR6 (
    input  a, b, c, d, e, f,
    output y
);
    assign y = a | b | c | d | e | f;
endmodule

modules/or4.v
module OR4 (
    input  a, b, c, d,
    output y
);
    assign y = a | b | c | d;
endmodule

modules/or9.v
module OR9 (
    input  a, b, c, d, e, f, g, h, i,
    output y
);
    assign y = a | b | c | d | e | f | g | h | i;
endmodule

modules/or8.v
module OR8 (
    input  a, b, c, d, e, f, g, h,
    output y
);
    assign y = a | b | c | d | e | f | g | h;
endmodule

modules/dec.v
//=================================================
// 4-to-16 Decoder
//=================================================
module Decoder4to16(
    input  [3:0] A,      // 4-bit input
    output reg [15:0] Y  // 16-bit one-hot output
);

    always @(*) begin
        case (A)
            4'b0000: Y = 16'b0000000000000001;
            4'b0001: Y = 16'b0000000000000010;
            4'b0010: Y = 16'b0000000000000100;
            4'b0011: Y = 16'b0000000000001000;
            4'b0100: Y = 16'b0000000000010000;
            4'b0101: Y = 16'b0000000000100000;
            4'b0110: Y = 16'b0000000001000000;
            4'b0111: Y = 16'b0000000010000000;
            4'b1000: Y = 16'b0000000100000000;
            4'b1001: Y = 16'b0000001000000000;
            4'b1010: Y = 16'b0000010000000000;
            4'b1011: Y = 16'b0000100000000000;
            4'b1100: Y = 16'b0001000000000000;
            4'b1101: Y = 16'b0010000000000000;
            4'b1110: Y = 16'b0100000000000000;
            4'b1111: Y = 16'b1000000000000000;
            default: Y = 16'b0000000000000000;
        endcase
    end

endmodule

main/seg7v.v
`timescale 1ns/1ps

`include "../modules/dec.v"
`include "../modules/or4.v"
`include "../modules/or6.v"
`include "../modules/or7.v"
`include "../modules/or8.v"
`include "../modules/or9.v"


module seg7v(
    input wire clk,
    input wire [3:0] nibble,
    output wire [6:0] seg
);

wire [15:0] decoded_vals;

// instantiate 4-to-16 decoder (module name is Decoder4to16, ports A -> input, Y -> one-hot output)
Decoder4to16 decoder_inst(.A(nibble), .Y(decoded_vals));

// instantiate OR gates (module names are OR4/OR6/OR7/OR8/OR9)
OR8 led1(.a(decoded_vals[0]), .b(decoded_vals[2]), .c(decoded_vals[3]), .d(decoded_vals[5]), .e(decoded_vals[6]), .f(decoded_vals[7]), .g(decoded_vals[8]), .h(decoded_vals[9]), .y(seg[0]));
OR8 led2(.a(decoded_vals[0]), .b(decoded_vals[1]), .c(decoded_vals[2]), .d(decoded_vals[3]), .e(decoded_vals[4]), .f(decoded_vals[7]), .g(decoded_vals[8]), .h(decoded_vals[9]), .y(seg[1]));
OR9 led3(.a(decoded_vals[0]), .b(decoded_vals[1]), .c(decoded_vals[3]), .d(decoded_vals[4]), .e(decoded_vals[5]), .f(decoded_vals[6]), .g(decoded_vals[7]), .h(decoded_vals[8]), .i(decoded_vals[9]), .y(seg[2]));
OR7 led4(.a(decoded_vals[0]), .b(decoded_vals[2]), .c(decoded_vals[3]), .d(decoded_vals[5]), .e(decoded_vals[6]), .f(decoded_vals[8]), .g(decoded_vals[9]), .y(seg[3]));
OR4 led5(.a(decoded_vals[0]), .b(decoded_vals[2]), .c(decoded_vals[6]), .d(decoded_vals[8]), .y(seg[4]));
OR6 led6(.a(decoded_vals[0]), .b(decoded_vals[4]), .c(decoded_vals[5]), .d(decoded_vals[6]), .e(decoded_vals[8]), .f(decoded_vals[9]), .y(seg[5]));
OR7 led7(.a(decoded_vals[2]), .b(decoded_vals[3]), .c(decoded_vals[4]), .d(decoded_vals[5]), .e(decoded_vals[6]), .f(decoded_vals[8]), .g(decoded_vals[9]), .y(seg[6]));

endmodule

main/seg7v_tb.v
`timescale 1ns/1ps

module seg7v_tb;
    reg clk;
    reg [3:0] nibble;
    wire [6:0] seg;
    wire [6:0] seg_ordered;
    assign seg_ordered = {seg[0], seg[1], seg[2], seg[3], seg[4], seg[5], seg[6]};

    // DUT
    seg7v uut (
        .clk(clk),
        .nibble(nibble),
        .seg(seg)
    );

    // 10 ns clock period
    initial clk = 0;
    always #5 clk = ~clk;

    initial begin
        $dumpfile("seg7v_tb.vcd");
        $dumpvars(0, seg7v_tb);
        $display("clk\tseg1..7");

        // loop through all the numbers from (0-15)
        nibble = 4'b0000; @(posedge clk); @(negedge clk); #1; $display("%b\t%b", clk, seg_ordered); // 0
        nibble = 4'b0001; @(posedge clk); @(negedge clk); #1; $display("%b\t%b", clk, seg_ordered); // 1
        nibble = 4'b0010; @(posedge clk); @(negedge clk); #1; $display("%b\t%b", clk, seg_ordered); // 2
        nibble = 4'b0011; @(posedge clk); @(negedge clk); #1; $display("%b\t%b", clk, seg_ordered); // 3
        nibble = 4'b0100; @(posedge clk); @(negedge clk); #1; $display("%b\t%b", clk, seg_ordered); // 4
        nibble = 4'b0101; @(posedge clk); @(negedge clk); #1; $display("%b\t%b", clk, seg_ordered); // 5
        nibble = 4'b0110; @(posedge clk); @(negedge clk); #1; $display("%b\t%b", clk, seg_ordered); // 6
        nibble = 4'b0111; @(posedge clk); @(negedge clk); #1; $display("%b\t%b", clk, seg_ordered); // 7
        nibble = 4'b1000; @(posedge clk); @(negedge clk); #1; $display("%b\t%b", clk, seg_ordered); // 8
        nibble = 4'b1001; @(posedge clk); @(negedge clk); #1; $display("%b\t%b", clk, seg_ordered); // 9
        nibble = 4'b1010; @(posedge clk); @(negedge clk); #1; $display("%b\t%b", clk, seg_ordered); // 10

        // custom test cases (2, 5, 8, 3)
        nibble = 4'b0010; @(posedge clk); @(negedge clk); #1; $display("%b\t%b", clk, seg_ordered); 
        nibble = 4'b0101; @(posedge clk); @(negedge clk); #1; $display("%b\t%b", clk, seg_ordered);
        nibble = 4'b1000; @(posedge clk); @(negedge clk); #1; $display("%b\t%b", clk, seg_ordered);
        nibble = 4'b0011; @(posedge clk); @(negedge clk); #1; $display("%b\t%b", clk, seg_ordered);

        @(posedge clk);
        #10 $finish;
    end
endmodule

main/seg7v_tb.vcd
$date
	Wed Nov 05 12:37:35 2025
$end
$version
	Icarus Verilog
$end
$timescale
	1ps
$end
$scope module seg7v_tb $end
$var wire 7 ! seg_ordered [6:0] $end
$var wire 7 " seg [6:0] $end
$var reg 1 # clk $end
$var reg 4 $ nibble [3:0] $end
$scope module uut $end
$var wire 1 # clk $end
$var wire 4 % nibble [3:0] $end
$var wire 7 & seg [6:0] $end
$var wire 16 ' decoded_vals [15:0] $end
$scope module decoder_inst $end
$var wire 4 ( A [3:0] $end
$var reg 16 ) Y [15:0] $end
$upscope $end
$scope module led1 $end
$var wire 1 * a $end
$var wire 1 + b $end
$var wire 1 , c $end
$var wire 1 - d $end
$var wire 1 . e $end
$var wire 1 / f $end
$var wire 1 0 g $end
$var wire 1 1 h $end
$var wire 1 2 y $end
$upscope $end
$scope module led2 $end
$var wire 1 3 a $end
$var wire 1 4 b $end
$var wire 1 5 c $end
$var wire 1 6 d $end
$var wire 1 7 e $end
$var wire 1 8 f $end
$var wire 1 9 g $end
$var wire 1 : h $end
$var wire 1 ; y $end
$upscope $end
$scope module led3 $end
$var wire 1 < a $end
$var wire 1 = b $end
$var wire 1 > c $end
$var wire 1 ? d $end
$var wire 1 @ e $end
$var wire 1 A f $end
$var wire 1 B g $end
$var wire 1 C h $end
$var wire 1 D i $end
$var wire 1 E y $end
$upscope $end
$scope module led4 $end
$var wire 1 F a $end
$var wire 1 G b $end
$var wire 1 H c $end
$var wire 1 I d $end
$var wire 1 J e $end
$var wire 1 K f $end
$var wire 1 L g $end
$var wire 1 M y $end
$upscope $end
$scope module led5 $end
$var wire 1 N a $end
$var wire 1 O b $end
$var wire 1 P c $end
$var wire 1 Q d $end
$var wire 1 R y $end
$upscope $end
$scope module led6 $end
$var wire 1 S a $end
$var wire 1 T b $end
$var wire 1 U c $end
$var wire 1 V d $end
$var wire 1 W e $end
$var wire 1 X f $end
$var wire 1 Y y $end
$upscope $end
$scope module led7 $end
$var wire 1 Z a $end
$var wire 1 [ b $end
$var wire 1 \ c $end
$var wire 1 ] d $end
$var wire 1 ^ e $end
$var wire 1 _ f $end
$var wire 1 ` g $end
$var wire 1 a y $end
$upscope $end
$upscope $end
$upscope $end
$enddefinitions $end
$comment Show the parameter values. $end
$dumpall
$end
#0
$dumpvars
0a
0`
0_
0^
0]
0\
0[
0Z
1Y
0X
0W
0V
0U
0T
1S
1R
0Q
0P
0O
1N
1M
0L
0K
0J
0I
0H
0G
1F
1E
0D
0C
0B
0A
0@
0?
0>
0=
1<
1;
0:
09
08
07
06
05
04
13
12
01
00
0/
0.
0-
0,
0+
1*
b1 )
b0 (
b1 '
b111111 &
b0 %
b0 $
0#
b111111 "
b1111110 !
$end
#5000
1#
#10000
0#
#11000
02
0M
0Y
b110000 !
b110 "
b110 &
0R
0S
0N
0F
1=
0<
14
03
0*
b10 '
b10 )
b1 $
b1 %
b1 (
#15000
1#
#20000
0#
#21000
0E
12
1a
1M
b1101101 !
b1011011 "
b1011011 &
1R
1Z
1O
1G
0=
15
04
1+
b100 '
b100 )
b10 $
b10 %
b10 (
#25000
1#
#30000
0#
#31000
1E
b1111001 !
b1001111 "
b1001111 &
0R
1[
0Z
0O
1H
0G
1>
16
05
1,
0+
b1000 '
b1000 )
b11 $
b11 %
b11 (
#35000
1#
#40000
0#
#41000
b110011 !
02
1Y
b1100110 "
b1100110 &
0M
1\
0[
1T
0H
1?
0>
17
06
0,
b10000 '
b10000 )
b100 $
b100 %
b100 (
#45000
1#
#50000
0#
#51000
b1011011 !
12
1M
b1101101 "
b1101101 &
0;
1]
0\
1U
0T
1I
1@
0?
07
1-
b100000 '
b100000 )
b101 $
b101 %
b101 (
#55000
1#
#60000
0#
#61000
b1011111 !
b1111101 "
b1111101 &
1R
1^
0]
1V
0U
1P
1J
0I
1A
0@
1.
0-
b1000000 '
b1000000 )
b110 $
b110 %
b110 (
#65000
1#
#70000
0#
#71000
0a
0Y
b1110000 !
0M
1;
b111 "
b111 &
0R
0^
0V
0P
0J
1B
0A
18
1/
0.
b10000000 '
b10000000 )
b111 $
b111 %
b111 (
#75000
1#
#80000
0#
#81000
1a
1Y
b1111111 !
1M
b1111111 "
b1111111 &
1R
1_
1W
1Q
1K
1C
0B
19
08
10
0/
b100000000 '
b100000000 )
b1000 $
b1000 %
b1000 (
#85000
1#
#90000
0#
#91000
b1111011 !
b1101111 "
b1101111 &
0R
1`
0_
1X
0W
0Q
1L
0K
1D
0C
1:
09
11
00
b1000000000 '
b1000000000 )
b1001 $
b1001 %
b1001 (
#95000
1#
#100000
0#
#101000
b0 !
0a
0Y
0M
0E
0;
b0 "
b0 &
02
0`
0X
0L
0D
0:
01
b10000000000 '
b10000000000 )
b1010 $
b1010 %
b1010 (
#105000
1#
#110000
0#
#111000
12
1a
1M
1;
b1101101 !
b1011011 "
b1011011 &
1R
1Z
1O
1G
15
1+
b100 '
b100 )
b10 $
b10 %
b10 (
#115000
1#
#120000
0#
#121000
0;
1E
1Y
b1011011 !
b1101101 "
b1101101 &
0R
1]
0Z
1U
0O
1I
0G
1@
05
1-
0+
b100000 '
b100000 )
b101 $
b101 %
b101 (
#125000
1#
#130000
0#
#131000
b1111111 !
1;
b1111111 "
b1111111 &
1R
1_
0]
1W
0U
1Q
1K
0I
1C
0@
19
10
0-
b100000000 '
b100000000 )
b1000 $
b1000 %
b1000 (
#135000
1#
#140000
0#
#141000
1a
0Y
b1111001 !
1M
1E
1;
12
b1001111 "
b1001111 &
0R
0_
1[
0W
0Q
0K
1H
0C
1>
09
16
00
1,
b1000 '
b1000 )
b11 $
b11 %
b11 (
